dppy/__init__.py
dppy/beta_ensemble_polynomial_potential.py
dppy/beta_ensemble_polynomial_potential_core.py
dppy/beta_ensembles.py
dppy/bless.py
dppy/exact_sampling.py
dppy/exotic_dpps.py
dppy/exotic_dpps_core.py
dppy/finite_dpps.py
dppy/intermediate_sampling.py
dppy/mcmc_sampling.py
dppy/multivariate_jacobi_ope.py
dppy/random_matrices.py
dppy/utils.py
dppy-0.3.3.dist-info/LICENSE
dppy-0.3.3.dist-info/METADATA
dppy-0.3.3.dist-info/WHEEL
dppy-0.3.3.dist-info/top_level.txt
dppy-0.3.3.dist-info/RECORD
