Metadata-Version: 2.1
Name: dppy
Version: 0.3.3
Summary: DPPy is a Python library for exact and approximate sampling of Determinantal Point Processes.
Home-page: https://github.com/guilgautier/DPPy
Author: Guillaume Gautier
Author-email: guillaume.gga@gmail.com
License: MIT
Project-URL: Companion paper, https://github.com/guilgautier/DPPy_paper
Project-URL: arXiv, https://arxiv.org/abs/1809.07258
Project-URL: Coverage, https://coveralls.io/github/guilgautier/DPPy?branch=master
Project-URL: Travis, https://travis-ci.com/guilgautier/DPPy
Project-URL: Documentation, https://dppy.readthedocs.io/en/latest/
Project-URL: Source code, https://github.com/guilgautier/DPPy
Keywords: Determinantal Point Processes,sampling schemes,random matrices
Classifier: Development Status :: 4 - Beta
Classifier: Intended Audience :: Science/Research
Classifier: Topic :: Scientific/Engineering :: Mathematics
Classifier: Topic :: Scientific/Engineering :: Artificial Intelligence
Classifier: License :: OSI Approved :: MIT License
Classifier: Programming Language :: Python :: 3.6
Classifier: Programming Language :: Python :: 3.7
Classifier: Operating System :: Unix
License-File: LICENSE
Requires-Dist: numpy
Requires-Dist: scipy >=1.1.0
Requires-Dist: matplotlib
Provides-Extra: docs
Requires-Dist: sphinxcontrib-bibtex ; extra == 'docs'
Requires-Dist: sphinx-rtd-theme ; extra == 'docs'
Provides-Extra: trees
Requires-Dist: networkx ; extra == 'trees'
Provides-Extra: zonotope
Requires-Dist: cvxopt ==1.2.1 ; extra == 'zonotope'
